eizen_sdk/__init__.py
eizen_sdk/main.py
eizen_sdk-0.1.13.dist-info/METADATA
eizen_sdk-0.1.13.dist-info/WHEEL
eizen_sdk-0.1.13.dist-info/top_level.txt
eizen_sdk-0.1.13.dist-info/RECORD
