Metadata-Version: 2.4
Name: eizen-sdk
Version: 0.1.13
Summary: A SDK to consume Eizen services
Author: Pardhu
License: MIT
Keywords: eizen sdk
Classifier: Programming Language :: Python :: 3
Classifier: License :: OSI Approved :: MIT License
Classifier: Operating System :: OS Independent
Classifier: Intended Audience :: Developers
Classifier: Topic :: Software Development :: Libraries
Requires-Python: >=3.6
Requires-Dist: PyJWT>=2.10.1
Requires-Dist: requests>=2.31.0
Requires-Dist: urllib3>=2.0.7
Requires-Dist: pyyaml>=6.0.2
Dynamic: author
Dynamic: classifier
Dynamic: description
Dynamic: description-content-type
Dynamic: keywords
Dynamic: license
Dynamic: requires-dist
Dynamic: requires-python
Dynamic: summary
